rougail/cli/__init__.py
rougail/cli/__main__.py
rougail/cli/i18n.py
rougail/cli/locale/fr/LC_MESSAGES/rougail_cli.mo
rougail_cli-0.1.1.dist-info/entry_points.txt
rougail_cli-0.1.1.dist-info/LICENSE
rougail_cli-0.1.1.dist-info/WHEEL
rougail_cli-0.1.1.dist-info/METADATA
rougail_cli-0.1.1.dist-info/RECORD
